eyetrax/__init__.py
eyetrax/_version.py
eyetrax/cli.py
eyetrax/constants.py
eyetrax/gaze.py
eyetrax/app/__init__.py
eyetrax/app/build_model.py
eyetrax/app/demo.py
eyetrax/app/virtualcam.py
eyetrax/calibration/__init__.py
eyetrax/calibration/adaptive.py
eyetrax/calibration/common.py
eyetrax/calibration/five_point.py
eyetrax/calibration/lissajous.py
eyetrax/calibration/nine_point.py
eyetrax/filters/__init__.py
eyetrax/filters/base.py
eyetrax/filters/kalman.py
eyetrax/filters/kde.py
eyetrax/filters/noop.py
eyetrax/models/__init__.py
eyetrax/models/base.py
eyetrax/models/elastic_net.py
eyetrax/models/ridge.py
eyetrax/models/svr.py
eyetrax/models/tiny_mlp.py
eyetrax/utils/draw.py
eyetrax/utils/screen.py
eyetrax/utils/video.py
eyetrax-0.3.1.dist-info/METADATA
eyetrax-0.3.1.dist-info/WHEEL
eyetrax-0.3.1.dist-info/entry_points.txt
eyetrax-0.3.1.dist-info/licenses/LICENSE
eyetrax-0.3.1.dist-info/RECORD
