Metadata-Version: 2.4
Name: eyetrax
Version: 0.3.1
Summary: Webcam-based eye-tracking
Project-URL: homepage, https://github.com/ck-zhang/eyetrax
Author: Chenkai Zhang (ck-zhang)
License: MIT License
License-File: LICENSE
Classifier: License :: OSI Approved :: MIT License
Classifier: Operating System :: OS Independent
Classifier: Programming Language :: Python :: 3
Classifier: Programming Language :: Python :: 3 :: Only
Requires-Python: >=3.9
Requires-Dist: mediapipe>=0.10
Requires-Dist: numpy>=1.22
Requires-Dist: opencv-python>=4.5
Requires-Dist: pyvirtualcam>=0.10
Requires-Dist: scikit-learn>=1.3
Requires-Dist: scipy>=1.10
Requires-Dist: screeninfo>=0.8
